bad_framework/__init__.py
bad_framework/bad_candidates/__init__.py
bad_framework/bad_candidates/dummy.py
bad_framework/bad_candidates/feature_bagging.py
bad_framework/bad_candidates/iforest.py
bad_framework/bad_candidates/knn.py
bad_framework/bad_candidates/loci.py
bad_framework/bad_candidates/lof.py
bad_framework/bad_candidates/ocsvm.py
bad_framework/bad_candidates/partknn.py
bad_framework/bad_client/__init__.py
bad_framework/bad_client/cli.py
bad_framework/bad_client/monitor.py
bad_framework/bad_client/ui.py
bad_framework/bad_master/__init__.py
bad_framework/bad_master/models.py
bad_framework/bad_master/server.py
bad_framework/bad_master/views.py
bad_framework/bad_master/templates/experiment_details.html
bad_framework/bad_master/templates/index.html
bad_framework/bad_master/templates/suite_details.html
bad_framework/bad_utils/__init__.py
bad_framework/bad_utils/adt.py
bad_framework/bad_utils/errors.py
bad_framework/bad_utils/files.py
bad_framework/bad_utils/magic.py
bad_framework/bad_utils/network.py
bad_framework/bad_worker/__init__.py
bad_framework/bad_worker/server.py
bad_framework/bad_worker/views.py
bad_framework/bad_worker/templates/index.html
bad_framework/include/bin/start_master.sh
bad_framework/include/bin/start_worker.sh
bad_framework/include/bin/stop_master.sh
bad_framework/include/bin/stop_worker.sh
bad_framework/include/data/annthyroid.arff
bad_framework/include/data/covertype.arff
bad_framework/include/data/dummy.arff
bad_framework/include/data/glass.arff
bad_framework/include/data/kdd99.arff
bad_framework/include/data/pendigits.arff
bad_framework/include/data/shuttle.arff
bad_framework/include/data/wbc.arff
bad_framework/include/data/wine.arff
bad_framework/include/defaults/bad.conf
bad_framework/include/defaults/candidate_parameters.txt
bad_framework/include/defaults/candidate_requirements.txt
bad_framework/include/defaults/workers
tests/__init__.py
tests/conftest.py
tests/bad_candidates/__init__.py
tests/bad_candidates/test_dummy.py
bad_framework-0.1.3.dist-info/LICENSE
bad_framework-0.1.3.dist-info/METADATA
bad_framework-0.1.3.dist-info/WHEEL
bad_framework-0.1.3.dist-info/entry_points.txt
bad_framework-0.1.3.dist-info/top_level.txt
bad_framework-0.1.3.dist-info/RECORD
