Metadata-Version: 2.1
Name: bad-framework
Version: 0.1.3
Summary: Benchmarking Anomaly Detection (BAD) framework.
Home-page: UNKNOWN
Author: Sivam Pasupathipillai
Author-email: sivam.pasupathipillai@gmail.com
License: UNKNOWN
Platform: UNKNOWN
Classifier: Programming Language :: Python :: 3
Classifier: Operating System :: OS Independent
Requires-Python: >=3.6
Requires-Dist: httpx
Requires-Dist: Jinja2
Requires-Dist: matplotlib
Requires-Dist: numpy
Requires-Dist: pyod
Requires-Dist: requests
Requires-Dist: scikit-learn
Requires-Dist: tornado
